Metadata-Version: 2.1
Name: pydroid-ipcam
Version: 2.0.0
Summary: Library for handling the Android IP Webcam app
Home-page: https://github.com/home-assistant-libs/pydroid-ipcam
Author: Pascal Vizeli
Author-email: pvizeli@syshack.ch
License: Apache License 2.0
Platform: any
Classifier: Intended Audience :: Developers
Classifier: Operating System :: OS Independent
Classifier: Programming Language :: Python
Classifier: Programming Language :: Python :: 3
Classifier: Topic :: Software Development :: Libraries :: Python Modules
Requires-Python: >=3.8
License-File: LICENSE
Requires-Dist: aiohttp (>=3.6.2)
